setup.py
detdup/__init__.py
detdup/core.py
detdup/utils.py
detdup.egg-info/PKG-INFO
detdup.egg-info/SOURCES.txt
detdup.egg-info/dependency_links.txt
detdup.egg-info/not-zip-safe
detdup.egg-info/pbr.json
detdup.egg-info/requires.txt
detdup.egg-info/top_level.txt
detdup/data_model/__init__.py
detdup/data_model/base.py
detdup/data_model/fake_item_ids.py
detdup/features/__init__.py
detdup/features/default.py
detdup/services/__init__.py
detdup/services/api.py
detdup/services/task.py