Metadata-Version: 1.1
Name: detdup
Version: 0.0.2
Summary: Detect duplicated items.
Home-page: http://github.com/17zuoye/detdup/
Author: David Chen
Author-email: mvjome@gmail.com
License: MIT
Platform: any
Classifier: Intended Audience :: Developers
Classifier: Operating System :: OS Independent
Classifier: Programming Language :: Python
Classifier: Topic :: Software Development :: Libraries :: Python Modules
